MANIFEST.in
README.rst
setup.py
Touchandgo.egg-info/PKG-INFO
Touchandgo.egg-info/SOURCES.txt
Touchandgo.egg-info/dependency_links.txt
Touchandgo.egg-info/entry_points.txt
Touchandgo.egg-info/requires.txt
Touchandgo.egg-info/top_level.txt
touchandgo/__init__.py
touchandgo/constants.py
touchandgo/decorators.py
touchandgo/helpers.py
touchandgo/history.py
touchandgo/lock.py
touchandgo/logger.py
touchandgo/main.py
touchandgo/output.py
touchandgo/settings.py
touchandgo/stream_server.py
touchandgo/download/__init__.py
touchandgo/download/moov.py
touchandgo/download/strategy.py
touchandgo/download/subtitles.py
touchandgo/search/__init__.py
touchandgo/search/leetx.py
touchandgo/search/skytorrents.py
touchandgo/templates/settings.yaml
touchandgo/tsproxy/__init__.py
touchandgo/tsproxy/templates/m3u.j2
touchandgo/tsproxy/templates/main.html