Metadata-Version: 1.0
Name: Touchandgo
Version: 0.14.2
Summary: A python app and library to watch series magically
Home-page: https://github.com/touchandgo-devs/touchandgo/
Author: Felipe Lerena, Nicolás Demarchi
Author-email: felipelerena@gmail.com - mail@gilgamezh.me
License: LICENSE.txt
Platform: UNKNOWN
